hf_seo_analyzer/__init__.py
hf_seo_analyzer/analyzer.py
hf_seo_analyzer/cli.py
hf_seo_analyzer/parser.py
hf_seo_analyzer/utils.py
hf_seo_analyzer-0.1.4.dist-info/METADATA
hf_seo_analyzer-0.1.4.dist-info/WHEEL
hf_seo_analyzer-0.1.4.dist-info/entry_points.txt
hf_seo_analyzer-0.1.4.dist-info/top_level.txt
hf_seo_analyzer-0.1.4.dist-info/RECORD
